trianglelite/__init__.py
trianglelite/__init__.pyi
trianglelite/pytrianglelite.cp312-win_amd64.pyd
trianglelite/pytrianglelite.pyi
trianglelite-0.1.0.dist-info/METADATA
trianglelite-0.1.0.dist-info/WHEEL
trianglelite-0.1.0.dist-info/licenses/LICENSE
trianglelite-0.1.0.dist-info/RECORD
