Metadata-Version: 2.1
Name: trianglelite
Version: 0.1.0
Summary: A lite wrapper around Shewchuk's triangle.
Maintainer-Email: Qingnan Zhou <qnzhou@gmail.com>
Requires-Python: >=3.9
